{
  "code": 200,
  "message": null,
  "data": {
      "productId": "PR-IC04400002000043SIYAH",
      "name": "adidas Erkek Sweatshirt IC0440",
      "image": "https://raw.githubusercontent.com/environmenttest/dummydata/main/images/PR-IC04400002000043SIYAH.webp",
      "price": "1.699,00 TL",
      "description": " <p><b>Materyal:</b> %70 Pamuk, %30 Geri Dönüştürülmüş Polyester</p><p><b>Tanımlama:</b> Adidas Erkek Sweatshirt</p>",
      "estimatedShipmentDate": "3 İş Gününde Kargoda",
      "priceUpdateDate": "11-08-2023"
  }
}
